killable_sudo
