Metadata-Version: 2.2
Name: killable-sudo
Version: 1.0.1
Summary: Wrapper around sudo which can be killed by the user who spawned the process.
Home-page: https://github.com/talwrii/killable-sudo
Author: @readwithai
Author-email: talwrii@gmail.com
Classifier: Programming Language :: Python :: 3
Classifier: Operating System :: POSIX :: Linux
Requires-Python: >=3.6
Dynamic: author
Dynamic: author-email
Dynamic: classifier
Dynamic: description
Dynamic: description-content-type
Dynamic: home-page
Dynamic: requires-python
Dynamic: summary
